NikGapps_Helper/AppSet.py
NikGapps_Helper/Args.py
NikGapps_Helper/Assets.py
NikGapps_Helper/B64.py
NikGapps_Helper/Cmd.py
NikGapps_Helper/Config.py
NikGapps_Helper/ConfigObj.py
NikGapps_Helper/FileOp.py
NikGapps_Helper/NikGappsConfig.py
NikGapps_Helper/P.py
NikGapps_Helper/Package.py
NikGapps_Helper/Statics.py
NikGapps_Helper/SystemStat.py
NikGapps_Helper/T.py
NikGapps_Helper/XmlOp.py
NikGapps_Helper/__init__.py
NikGapps_Helper/compression/CompOps.py
NikGapps_Helper/compression/Export.py
NikGapps_Helper/compression/Modes.py
NikGapps_Helper/compression/Tar.py
NikGapps_Helper/compression/Zip.py
NikGapps_Helper/compression/Zsh.py
NikGapps_Helper/compression/__init__.py
NikGapps_Helper/git/Git.py
NikGapps_Helper/git/GitOperations.py
NikGapps_Helper/git/GitStatics.py
NikGapps_Helper/git/__init__.py
NikGapps_Helper/web/Requests.py
NikGapps_Helper/web/TelegramApi.py
NikGapps_Helper/web/Upload.py
NikGapps_Helper/web/__init__.py
NikGapps_Helper-0.0.2.dist-info/LICENSE
NikGapps_Helper-0.0.2.dist-info/METADATA
NikGapps_Helper-0.0.2.dist-info/WHEEL
NikGapps_Helper-0.0.2.dist-info/top_level.txt
NikGapps_Helper-0.0.2.dist-info/RECORD
