Metadata-Version: 2.1
Name: NikGapps-Helper
Version: 0.0.2
Summary: A package that offers NikGapps helper classes
Author-email: Nikhil Menghani <nikgapps@gmail.com>
Project-URL: Homepage, https://github.com/nikgapps/helper
Project-URL: Bug Tracker, https://github.com/nikgapps/helper/issues
Classifier: Programming Language :: Python :: 3
Classifier: License :: OSI Approved :: MIT License
Classifier: Operating System :: OS Independent
Requires-Python: >=3.7
License-File: LICENSE
